altf1be_helpers/__init__.py
altf1be_helpers/altf1be_helpers.py
altf1be_helpers/altf1be_helpers_azure_storage.py
altf1be_helpers/altf1be_helpers_unittest.py
altf1be_helpers/altf1be_json_helpers_unittest.py
altf1be_helpers/sql_statement_helpers.py
altf1be_helpers-2.2.2.dist-info/LICENSE
altf1be_helpers-2.2.2.dist-info/METADATA
altf1be_helpers-2.2.2.dist-info/WHEEL
altf1be_helpers-2.2.2.dist-info/top_level.txt
altf1be_helpers-2.2.2.dist-info/RECORD
