Metadata-Version: 2.1
Name: altf1be-helpers
Version: 2.2.2
Summary: Helpers to deal with basic requirements of an application built by www.alt-f1.be
Home-page: https://github.com/ALT-F1/altf1be_helpers
Author: Abdelkrim Boujraf
Author-email: abo+altf1be_helpers_pkg@alt-f1.be
License: EUPL-1.2
Project-URL: Bug Reports, https://github.com/ALT-F1/altf1be_helpers/issues/new
Project-URL: Company behind the library, http://www.alt-f1.be
Project-URL: Source, https://github.com/ALT-F1/altf1be_helpers
Keywords: library,altf1be_helpers,alt-f1.be,helpers-library,python3,pypi-package
Platform: UNKNOWN
Classifier: Development Status :: 5 - Production/Stable
Classifier: Intended Audience :: Developers
Classifier: License :: OSI Approved :: European Union Public Licence 1.2 (EUPL 1.2)
Classifier: Operating System :: OS Independent
Classifier: Programming Language :: Python :: 3.7
Classifier: Topic :: Software Development :: Libraries :: Python Modules
Requires-Python: >=3.5
Requires-Dist: python-dateutil (==2.8.1)
Requires-Dist: requests (==2.25.0)
Requires-Dist: Unidecode (==1.1.1)
